cloud_ds_api/__init__.py
cloud_ds_api/cloud_api.py
cloud_ds_api/resources.py
cloud_ds_api-1.2.11.dist-info/licenses/LICENSE
cloud_ds_api-1.2.11.dist-info/METADATA
cloud_ds_api-1.2.11.dist-info/WHEEL
cloud_ds_api-1.2.11.dist-info/top_level.txt
cloud_ds_api-1.2.11.dist-info/RECORD
