Metadata-Version: 2.4
Name: cloud-ds-api
Version: 1.2.11
Summary: cloud-ds-api
Home-page: https://github.com/MartinSahlen/cloud-functions-python
Download-URL: https://github.com/MartinSahlen/cloud-functions-python
Author: Martin Sahlen
Author-email: msahlen@alvinnet.com
Project-URL: Documentation, https://github.com/MartinSahlen/cloud-functions-python
License-File: LICENSE
Dynamic: author
Dynamic: author-email
Dynamic: description
Dynamic: description-content-type
Dynamic: download-url
Dynamic: home-page
Dynamic: license-file
Dynamic: project-url
Dynamic: summary
